Metadata-Version: 1.0
Name: NDBD-distributions
Version: 0.1
Summary: Gaussian and Binomial distributions
Home-page: UNKNOWN
Author:  Tanvi Tiwari
Author-email: tanvitiwari1700@gmail.com
License: UNKNOWN
Platform: UNKNOWN
